pantsbuild.pants.contrib.avro-1.28.0-py3.6-nspkg.pth
pants/contrib/avro/register.py
pants/contrib/avro/target_types.py
pants/contrib/avro/targets/java_avro_library.py
pants/contrib/avro/tasks/avro_gen.py
pantsbuild.pants.contrib.avro-1.28.0.dist-info/METADATA
pantsbuild.pants.contrib.avro-1.28.0.dist-info/WHEEL
pantsbuild.pants.contrib.avro-1.28.0.dist-info/entry_points.txt
pantsbuild.pants.contrib.avro-1.28.0.dist-info/namespace_packages.txt
pantsbuild.pants.contrib.avro-1.28.0.dist-info/top_level.txt
pantsbuild.pants.contrib.avro-1.28.0.dist-info/zip-safe
pantsbuild.pants.contrib.avro-1.28.0.dist-info/RECORD
